{
  "lexicon": 1,
  "id": "fyi.unravel.frontpage.comment",
  "defs": {
    "main": {
      "type": "record",
      "description": "Record containing a Frontpage comment.",
      "key": "tid",
      "record": {
        "type": "object",
        "required": ["createdAt", "post"],
        "properties": {
          "content": {
            // TODO: richtext
          },
          "createdAt": {
            "type": "string",
            "format": "datetime",
            "description": "Client-declared timestamp when this comment was originally created."
          },
          "parent": { "type": "ref", "ref": "com.atproto.repo.strongRef" },
          "post": { "type": "ref", "ref": "com.atproto.repo.strongRef" }
        }
      }
    }
  }
}
